LICENSE
MANIFEST.in
README.md
setup.cfg
setup.py
voc
volvooncall/__init__.py
volvooncall/dashboard.py
volvooncall/mqtt.py
volvooncall/util.py
volvooncall/volvooncall.py
volvooncall.egg-info/PKG-INFO
volvooncall.egg-info/SOURCES.txt
volvooncall.egg-info/dependency_links.txt
volvooncall.egg-info/requires.txt
volvooncall.egg-info/top_level.txt