Metadata-Version: 2.1
Name: volvooncall
Version: 0.10.4
Summary: Communicate with VOC
Home-page: https://github.com/molobrakos/volvooncall
Author: Erik
Author-email: error.errorsson@gmail.com
Maintainer: decompil3d
License: Unlicense
Requires-Python: >=3.10
Provides-Extra: console
Provides-Extra: mqtt
License-File: LICENSE
